Workbook

Sheet Inputs
B1: REAL ESTATE INVESTMENT MODEL
B6: INPUTS & ASSUMPTIONS
B7: Blue = editable inputs | Black = formulas | All values in Indian Rupees (₹) unless stated
B9: A. PROPERTY DETAILS | E9: D. OPERATING EXPENSES
B10: Property type | C10: Residential – Apartment | E10: Property tax (₹/year) | F10: 18000
B11: Property location | C11: Gurugram, Haryana | E11: Maintenance / society (₹/year) | F11: 36000
B12: Built-up area (sq ft) | C12: 1200 | E12: Insurance premium (₹/year) | F12: 12000
B13: Purchase price (₹) | C13: 9000000 | E13: Management fee (% of income) | F13: 0.08
B14: Stamp duty & registration (%) | C14: 0.07 | E14: Repair / capex reserve (%) | F14: 0.05
B15: Other acquisition costs (₹) | C15: 150000 | E15: Management cost (₹) | F15: =C35*F13 -> 24729.6
B16: Total acquisition cost (₹) | C16: =C13+C13*C14+C15 -> 9780000 | E16: Capex reserve (₹) | F16: =C35*F14 -> 15456
E17: Total annual expenses (₹) | F17: =F10+F11+F12+F15+F16 -> 106185.6
B18: B. FINANCING & LOAN
B19: Down payment (%) | C19: 0.2 | E19: E. KEY RETURN METRICS (YEAR 1)
B20: Loan amount (₹) | C20: =C13*(1-C19) -> 7200000 | E20: NOI – Net Operating Income (₹) | F20: =C35-F17 -> 202934.4
B21: Loan interest rate (% p.a.) | C21: 0.0875 | E21: Gross rental yield (%) | F21: =C33/C13 -> 0.037333333
B22: Loan tenure (years) | C22: 20 | E22: Cap rate (%) | F22: =IF(C16>0,F20/C16,0) -> 0.020749939
B23: Processing fee (₹) | C23: 10000 | E23: Net cash flow after EMI (₹) | F23: =F20-C25 -> -560591.65
B24: Monthly EMI (₹) | C24: =IFERROR(C20*C21/12*(1+C21/12)^(C22*12)/((1+C21/12)^(C22*12)-1),0) -> 63627.171 | E24: Cash-on-cash return (%) | F24: =IF(C26>0,F23/C26,0) -> -0.21644465
B25: Annual EMI (₹) | C25: =C24*12 -> 763526.05 | E25: DSCR (x) | F25: =IF(C25>0,F20/C25,0) -> 0.26578582
B26: Initial equity deployed (₹) | C26: =C13*C19+C13*C14+C15+C23 -> 2590000 | E26: Price per sq ft (₹) | F26: =IF(C12>0,C13/C12,0) -> 7500
B28: C. RENTAL INCOME | E28: F. EXIT ASSUMPTIONS
B29: Monthly rent (₹) | C29: 28000 | E29: Hold period (years) | F29: 10
B30: Other monthly income (₹) | C30: 0 | E30: Annual appreciation (% p.a.) | F30: 0.07
B31: Annual rent escalation (%) | C31: 0.05 | E31: Selling cost (% of sale price) | F31: 0.02
B32: Vacancy rate (%) | C32: 0.08 | E32: Capital gains tax rate (%) | F32: 0.2
B33: Gross annual rent (₹) | C33: =(C29+C30)*12 -> 336000 | E33: Projected sale price (₹) | F33: =C13*(1+F30)^F29 -> 17704362
B34: Vacancy loss (₹) | C34: =C33*C32 -> 26880 | E34: Less: Selling costs (₹) | F34: =F33*F31 -> 354087.24
B35: Effective annual income (₹) | C35: =C33-C34 -> 309120 | E35: Less: Capital gains tax (₹) | F35: =MAX(0,(F33-C13)*F32) -> 1740872.4
E36: Net sale proceeds (₹) | F36: =F33-F34-F35 -> 15609403
E37: Total profit (rental + exit) (₹) | F37: =F36-C26 -> 13019403

Sheet Cash Flow
B1: ANNUAL CASH FLOW PROJECTION (10-Year Hold)
B2: All values in ₹. Rent escalates annually by the rate in Inputs!C26. EMI is fixed. Linked to Inputs sheet.
B4: Item | C4: Year 1 | D4: Year 2 | E4: Year 3 | F4: Year 4 | G4: Year 5 | H4: Year 6 | I4: Year 7 | J4: Year 8 | K4: Year 9 | L4: Year 10
B5: Gross annual rent (₹) | C5: =(Inputs!C29+Inputs!C30)*12*(1+Inputs!C31)^0 -> 336000 | D5: =(Inputs!C29+Inputs!C30)*12*(1+Inputs!C31)^1 -> 352800 | E5: =(Inputs!C29+Inputs!C30)*12*(1+Inputs!C31)^2 -> 370440 | F5: =(Inputs!C29+Inputs!C30)*12*(1+Inputs!C31)^3 -> 388962 | G5: =(Inputs!C29+Inputs!C30)*12*(1+Inputs!C31)^4 -> 408410.1 | H5: =(Inputs!C29+Inputs!C30)*12*(1+Inputs!C31)^5 -> 428830.61 | I5: =(Inputs!C29+Inputs!C30)*12*(1+Inputs!C31)^6 -> 450272.14 | J5: =(Inputs!C29+Inputs!C30)*12*(1+Inputs!C31)^7 -> 472785.74 | K5: =(Inputs!C29+Inputs!C30)*12*(1+Inputs!C31)^8 -> 496425.03 | L5: =(Inputs!C29+Inputs!C30)*12*(1+Inputs!C31)^9 -> 521246.28
B6: Less: Vacancy loss (₹) | C6: =-(Inputs!C29+Inputs!C30)*12*(1+Inputs!C31)^0*(1-Inputs!C32)/( (1-Inputs!C32) )*Inputs!C32 -> -26880 | D6: =-(Inputs!C29+Inputs!C30)*12*(1+Inputs!C31)^1*(1-Inputs!C32)/( (1-Inputs!C32) )*Inputs!C32 -> -28224 | E6: =-(Inputs!C29+Inputs!C30)*12*(1+Inputs!C31)^2*(1-Inputs!C32)/( (1-Inputs!C32) )*Inputs!C32 -> -29635.2 | F6: =-(Inputs!C29+Inputs!C30)*12*(1+Inputs!C31)^3*(1-Inputs!C32)/( (1-Inputs!C32) )*Inputs!C32 -> -31116.96 | G6: =-(Inputs!C29+Inputs!C30)*12*(1+Inputs!C31)^4*(1-Inputs!C32)/( (1-Inputs!C32) )*Inputs!C32 -> -32672.808 | H6: =-(Inputs!C29+Inputs!C30)*12*(1+Inputs!C31)^5*(1-Inputs!C32)/( (1-Inputs!C32) )*Inputs!C32 -> -34306.448 | I6: =-(Inputs!C29+Inputs!C30)*12*(1+Inputs!C31)^6*(1-Inputs!C32)/( (1-Inputs!C32) )*Inputs!C32 -> -36021.771 | J6: =-(Inputs!C29+Inputs!C30)*12*(1+Inputs!C31)^7*(1-Inputs!C32)/( (1-Inputs!C32) )*Inputs!C32 -> -37822.859 | K6: =-(Inputs!C29+Inputs!C30)*12*(1+Inputs!C31)^8*(1-Inputs!C32)/( (1-Inputs!C32) )*Inputs!C32 -> -39714.002 | L6: =-(Inputs!C29+Inputs!C30)*12*(1+Inputs!C31)^9*(1-Inputs!C32)/( (1-Inputs!C32) )*Inputs!C32 -> -41699.702
B7: Effective rental income (₹) | C7: =(Inputs!C29+Inputs!C30)*12*(1+Inputs!C31)^0*(1-Inputs!C32) -> 309120 | D7: =(Inputs!C29+Inputs!C30)*12*(1+Inputs!C31)^1*(1-Inputs!C32) -> 324576 | E7: =(Inputs!C29+Inputs!C30)*12*(1+Inputs!C31)^2*(1-Inputs!C32) -> 340804.8 | F7: =(Inputs!C29+Inputs!C30)*12*(1+Inputs!C31)^3*(1-Inputs!C32) -> 357845.04 | G7: =(Inputs!C29+Inputs!C30)*12*(1+Inputs!C31)^4*(1-Inputs!C32) -> 375737.29 | H7: =(Inputs!C29+Inputs!C30)*12*(1+Inputs!C31)^5*(1-Inputs!C32) -> 394524.16 | I7: =(Inputs!C29+Inputs!C30)*12*(1+Inputs!C31)^6*(1-Inputs!C32) -> 414250.36 | J7: =(Inputs!C29+Inputs!C30)*12*(1+Inputs!C31)^7*(1-Inputs!C32) -> 434962.88 | K7: =(Inputs!C29+Inputs!C30)*12*(1+Inputs!C31)^8*(1-Inputs!C32) -> 456711.03 | L7: =(Inputs!C29+Inputs!C30)*12*(1+Inputs!C31)^9*(1-Inputs!C32) -> 479546.58
B9: Less: Property tax (₹) | C9: =Inputs!F10 -> 18000 | D9: =Inputs!F10 -> 18000 | E9: =Inputs!F10 -> 18000 | F9: =Inputs!F10 -> 18000 | G9: =Inputs!F10 -> 18000 | H9: =Inputs!F10 -> 18000 | I9: =Inputs!F10 -> 18000 | J9: =Inputs!F10 -> 18000 | K9: =Inputs!F10 -> 18000 | L9: =Inputs!F10 -> 18000
B10: Less: Maintenance (₹) | C10: =Inputs!F11 -> 36000 | D10: =Inputs!F11 -> 36000 | E10: =Inputs!F11 -> 36000 | F10: =Inputs!F11 -> 36000 | G10: =Inputs!F11 -> 36000 | H10: =Inputs!F11 -> 36000 | I10: =Inputs!F11 -> 36000 | J10: =Inputs!F11 -> 36000 | K10: =Inputs!F11 -> 36000 | L10: =Inputs!F11 -> 36000
B11: Less: Insurance (₹) | C11: =Inputs!F12 -> 12000 | D11: =Inputs!F12 -> 12000 | E11: =Inputs!F12 -> 12000 | F11: =Inputs!F12 -> 12000 | G11: =Inputs!F12 -> 12000 | H11: =Inputs!F12 -> 12000 | I11: =Inputs!F12 -> 12000 | J11: =Inputs!F12 -> 12000 | K11: =Inputs!F12 -> 12000 | L11: =Inputs!F12 -> 12000
B12: Less: Mgmt fee (₹) | C12: =(Inputs!C29+Inputs!C30)*12*(1+Inputs!C31)^0*(1-Inputs!C32)*Inputs!F13 -> 24729.6 | D12: =(Inputs!C29+Inputs!C30)*12*(1+Inputs!C31)^1*(1-Inputs!C32)*Inputs!F13 -> 25966.08 | E12: =(Inputs!C29+Inputs!C30)*12*(1+Inputs!C31)^2*(1-Inputs!C32)*Inputs!F13 -> 27264.384 | F12: =(Inputs!C29+Inputs!C30)*12*(1+Inputs!C31)^3*(1-Inputs!C32)*Inputs!F13 -> 28627.603 | G12: =(Inputs!C29+Inputs!C30)*12*(1+Inputs!C31)^4*(1-Inputs!C32)*Inputs!F13 -> 30058.983 | H12: =(Inputs!C29+Inputs!C30)*12*(1+Inputs!C31)^5*(1-Inputs!C32)*Inputs!F13 -> 31561.933 | I12: =(Inputs!C29+Inputs!C30)*12*(1+Inputs!C31)^6*(1-Inputs!C32)*Inputs!F13 -> 33140.029 | J12: =(Inputs!C29+Inputs!C30)*12*(1+Inputs!C31)^7*(1-Inputs!C32)*Inputs!F13 -> 34797.031 | K12: =(Inputs!C29+Inputs!C30)*12*(1+Inputs!C31)^8*(1-Inputs!C32)*Inputs!F13 -> 36536.882 | L12: =(Inputs!C29+Inputs!C30)*12*(1+Inputs!C31)^9*(1-Inputs!C32)*Inputs!F13 -> 38363.726
B13: Less: Capex reserve (₹) | C13: =(Inputs!C29+Inputs!C30)*12*(1+Inputs!C31)^0*(1-Inputs!C32)*Inputs!F14 -> 15456 | D13: =(Inputs!C29+Inputs!C30)*12*(1+Inputs!C31)^1*(1-Inputs!C32)*Inputs!F14 -> 16228.8 | E13: =(Inputs!C29+Inputs!C30)*12*(1+Inputs!C31)^2*(1-Inputs!C32)*Inputs!F14 -> 17040.24 | F13: =(Inputs!C29+Inputs!C30)*12*(1+Inputs!C31)^3*(1-Inputs!C32)*Inputs!F14 -> 17892.252 | G13: =(Inputs!C29+Inputs!C30)*12*(1+Inputs!C31)^4*(1-Inputs!C32)*Inputs!F14 -> 18786.865 | H13: =(Inputs!C29+Inputs!C30)*12*(1+Inputs!C31)^5*(1-Inputs!C32)*Inputs!F14 -> 19726.208 | I13: =(Inputs!C29+Inputs!C30)*12*(1+Inputs!C31)^6*(1-Inputs!C32)*Inputs!F14 -> 20712.518 | J13: =(Inputs!C29+Inputs!C30)*12*(1+Inputs!C31)^7*(1-Inputs!C32)*Inputs!F14 -> 21748.144 | K13: =(Inputs!C29+Inputs!C30)*12*(1+Inputs!C31)^8*(1-Inputs!C32)*Inputs!F14 -> 22835.551 | L13: =(Inputs!C29+Inputs!C30)*12*(1+Inputs!C31)^9*(1-Inputs!C32)*Inputs!F14 -> 23977.329
B14: Total expenses (₹) | C14: =Inputs!F10+Inputs!F11+Inputs!F12+(Inputs!C29+Inputs!C30)*12*(1+Inputs!C31)^0*(1-Inputs!C32)*Inputs!F13+(Inputs!C29+Inputs!C30)*12*(1+Inputs!C31)^0*(1-Inputs!C32)*Inputs!F14 -> 106185.6 | D14: =Inputs!F10+Inputs!F11+Inputs!F12+(Inputs!C29+Inputs!C30)*12*(1+Inputs!C31)^1*(1-Inputs!C32)*Inputs!F13+(Inputs!C29+Inputs!C30)*12*(1+Inputs!C31)^1*(1-Inputs!C32)*Inputs!F14 -> 108194.88 | E14: =Inputs!F10+Inputs!F11+Inputs!F12+(Inputs!C29+Inputs!C30)*12*(1+Inputs!C31)^2*(1-Inputs!C32)*Inputs!F13+(Inputs!C29+Inputs!C30)*12*(1+Inputs!C31)^2*(1-Inputs!C32)*Inputs!F14 -> 110304.62 | F14: =Inputs!F10+Inputs!F11+Inputs!F12+(Inputs!C29+Inputs!C30)*12*(1+Inputs!C31)^3*(1-Inputs!C32)*Inputs!F13+(Inputs!C29+Inputs!C30)*12*(1+Inputs!C31)^3*(1-Inputs!C32)*Inputs!F14 -> 112519.86 | G14: =Inputs!F10+Inputs!F11+Inputs!F12+(Inputs!C29+Inputs!C30)*12*(1+Inputs!C31)^4*(1-Inputs!C32)*Inputs!F13+(Inputs!C29+Inputs!C30)*12*(1+Inputs!C31)^4*(1-Inputs!C32)*Inputs!F14 -> 114845.85 | H14: =Inputs!F10+Inputs!F11+Inputs!F12+(Inputs!C29+Inputs!C30)*12*(1+Inputs!C31)^5*(1-Inputs!C32)*Inputs!F13+(Inputs!C29+Inputs!C30)*12*(1+Inputs!C31)^5*(1-Inputs!C32)*Inputs!F14 -> 117288.14 | I14: =Inputs!F10+Inputs!F11+Inputs!F12+(Inputs!C29+Inputs!C30)*12*(1+Inputs!C31)^6*(1-Inputs!C32)*Inputs!F13+(Inputs!C29+Inputs!C30)*12*(1+Inputs!C31)^6*(1-Inputs!C32)*Inputs!F14 -> 119852.55 | J14: =Inputs!F10+Inputs!F11+Inputs!F12+(Inputs!C29+Inputs!C30)*12*(1+Inputs!C31)^7*(1-Inputs!C32)*Inputs!F13+(Inputs!C29+Inputs!C30)*12*(1+Inputs!C31)^7*(1-Inputs!C32)*Inputs!F14 -> 122545.17 | K14: =Inputs!F10+Inputs!F11+Inputs!F12+(Inputs!C29+Inputs!C30)*12*(1+Inputs!C31)^8*(1-Inputs!C32)*Inputs!F13+(Inputs!C29+Inputs!C30)*12*(1+Inputs!C31)^8*(1-Inputs!C32)*Inputs!F14 -> 125372.43 | L14: =Inputs!F10+Inputs!F11+Inputs!F12+(Inputs!C29+Inputs!C30)*12*(1+Inputs!C31)^9*(1-Inputs!C32)*Inputs!F13+(Inputs!C29+Inputs!C30)*12*(1+Inputs!C31)^9*(1-Inputs!C32)*Inputs!F14 -> 128341.06
B16: Net Operating Income – NOI (₹) | C16: =(Inputs!C29+Inputs!C30)*12*(1+Inputs!C31)^0*(1-Inputs!C32)*(1-Inputs!F13-Inputs!F14)-Inputs!F10-Inputs!F11-Inputs!F12 -> 202934.4 | D16: =(Inputs!C29+Inputs!C30)*12*(1+Inputs!C31)^1*(1-Inputs!C32)*(1-Inputs!F13-Inputs!F14)-Inputs!F10-Inputs!F11-Inputs!F12 -> 216381.12 | E16: =(Inputs!C29+Inputs!C30)*12*(1+Inputs!C31)^2*(1-Inputs!C32)*(1-Inputs!F13-Inputs!F14)-Inputs!F10-Inputs!F11-Inputs!F12 -> 230500.18 | F16: =(Inputs!C29+Inputs!C30)*12*(1+Inputs!C31)^3*(1-Inputs!C32)*(1-Inputs!F13-Inputs!F14)-Inputs!F10-Inputs!F11-Inputs!F12 -> 245325.18 | G16: =(Inputs!C29+Inputs!C30)*12*(1+Inputs!C31)^4*(1-Inputs!C32)*(1-Inputs!F13-Inputs!F14)-Inputs!F10-Inputs!F11-Inputs!F12 -> 260891.44 | H16: =(Inputs!C29+Inputs!C30)*12*(1+Inputs!C31)^5*(1-Inputs!C32)*(1-Inputs!F13-Inputs!F14)-Inputs!F10-Inputs!F11-Inputs!F12 -> 277236.02 | I16: =(Inputs!C29+Inputs!C30)*12*(1+Inputs!C31)^6*(1-Inputs!C32)*(1-Inputs!F13-Inputs!F14)-Inputs!F10-Inputs!F11-Inputs!F12 -> 294397.82 | J16: =(Inputs!C29+Inputs!C30)*12*(1+Inputs!C31)^7*(1-Inputs!C32)*(1-Inputs!F13-Inputs!F14)-Inputs!F10-Inputs!F11-Inputs!F12 -> 312417.71 | K16: =(Inputs!C29+Inputs!C30)*12*(1+Inputs!C31)^8*(1-Inputs!C32)*(1-Inputs!F13-Inputs!F14)-Inputs!F10-Inputs!F11-Inputs!F12 -> 331338.59 | L16: =(Inputs!C29+Inputs!C30)*12*(1+Inputs!C31)^9*(1-Inputs!C32)*(1-Inputs!F13-Inputs!F14)-Inputs!F10-Inputs!F11-Inputs!F12 -> 351205.52
B17: Less: Annual EMI (₹) | C17: =-Inputs!C25 -> -763526.05 | D17: =-Inputs!C25 -> -763526.05 | E17: =-Inputs!C25 -> -763526.05 | F17: =-Inputs!C25 -> -763526.05 | G17: =-Inputs!C25 -> -763526.05 | H17: =-Inputs!C25 -> -763526.05 | I17: =-Inputs!C25 -> -763526.05 | J17: =-Inputs!C25 -> -763526.05 | K17: =-Inputs!C25 -> -763526.05 | L17: =-Inputs!C25 -> -763526.05
B18: Net Cash Flow (₹) | C18: =(Inputs!C29+Inputs!C30)*12*(1+Inputs!C31)^0*(1-Inputs!C32)*(1-Inputs!F13-Inputs!F14)-Inputs!F10-Inputs!F11-Inputs!F12-Inputs!C25 -> -560591.65 | D18: =(Inputs!C29+Inputs!C30)*12*(1+Inputs!C31)^1*(1-Inputs!C32)*(1-Inputs!F13-Inputs!F14)-Inputs!F10-Inputs!F11-Inputs!F12-Inputs!C25 -> -547144.93 | E18: =(Inputs!C29+Inputs!C30)*12*(1+Inputs!C31)^2*(1-Inputs!C32)*(1-Inputs!F13-Inputs!F14)-Inputs!F10-Inputs!F11-Inputs!F12-Inputs!C25 -> -533025.88 | F18: =(Inputs!C29+Inputs!C30)*12*(1+Inputs!C31)^3*(1-Inputs!C32)*(1-Inputs!F13-Inputs!F14)-Inputs!F10-Inputs!F11-Inputs!F12-Inputs!C25 -> -518200.87 | G18: =(Inputs!C29+Inputs!C30)*12*(1+Inputs!C31)^4*(1-Inputs!C32)*(1-Inputs!F13-Inputs!F14)-Inputs!F10-Inputs!F11-Inputs!F12-Inputs!C25 -> -502634.61 | H18: =(Inputs!C29+Inputs!C30)*12*(1+Inputs!C31)^5*(1-Inputs!C32)*(1-Inputs!F13-Inputs!F14)-Inputs!F10-Inputs!F11-Inputs!F12-Inputs!C25 -> -486290.04 | I18: =(Inputs!C29+Inputs!C30)*12*(1+Inputs!C31)^6*(1-Inputs!C32)*(1-Inputs!F13-Inputs!F14)-Inputs!F10-Inputs!F11-Inputs!F12-Inputs!C25 -> -469128.24 | J18: =(Inputs!C29+Inputs!C30)*12*(1+Inputs!C31)^7*(1-Inputs!C32)*(1-Inputs!F13-Inputs!F14)-Inputs!F10-Inputs!F11-Inputs!F12-Inputs!C25 -> -451108.34 | K18: =(Inputs!C29+Inputs!C30)*12*(1+Inputs!C31)^8*(1-Inputs!C32)*(1-Inputs!F13-Inputs!F14)-Inputs!F10-Inputs!F11-Inputs!F12-Inputs!C25 -> -432187.46 | L18: =(Inputs!C29+Inputs!C30)*12*(1+Inputs!C31)^9*(1-Inputs!C32)*(1-Inputs!F13-Inputs!F14)-Inputs!F10-Inputs!F11-Inputs!F12-Inputs!C25 -> -412320.53
B20: Cumulative Cash Flow (₹) | C20: =C18 -> -560591.65 | D20: =C20+D18 -> -1107736.6 | E20: =D20+E18 -> -1640762.5 | F20: =E20+F18 -> -2158963.3 | G20: =F20+G18 -> -2661597.9 | H20: =G20+H18 -> -3147888 | I20: =H20+I18 -> -3617016.2 | J20: =I20+J18 -> -4068124.6 | K20: =J20+K18 -> -4500312 | L20: =K20+L18 -> -4912632.5

Sheet Scenarios
B1: SCENARIO STRESS TEST — Bear / Base / Bull
B2: Blue cells are editable. Outputs automatically recalculate. Change assumptions to test your model's resilience.
B4: Assumption | C4: Bear Case | D4: Base Case | E4: Bull Case
B5: Monthly rent (₹) | C5: 20000 | D5: 28000 | E5: 33000
B6: Vacancy rate (%) | C6: 0.15 | D6: 0.08 | E6: 0.04
B7: Rent escalation p.a. (%) | C7: 0.02 | D7: 0.05 | E7: 0.08
B8: Appreciation (% p.a.) | C8: 0.04 | D8: 0.07 | E8: 0.1
B9: Loan interest rate (%) | C9: 0.0925 | D9: 0.0875 | E9: 0.085
B10: Selling cost (%) | C10: 0.03 | D10: 0.02 | E10: 0.015
B11: Hold period (years) | C11: 10 | D11: 10 | E11: 10
B13: CALCULATED OUTPUTS
B14: Effective income (₹) | C14: =(C5*12*(1-C6)) -> 204000 | D14: =(D5*12*(1-D6)) -> 309120 | E14: =(E5*12*(1-E6)) -> 380160
B15: Total expenses (₹) | C15: =Inputs!F10+Inputs!F11+Inputs!F12+(C5*12*(1-C6))*Inputs!F13+(C5*12*(1-C6))*Inputs!F14 -> 92520 | D15: =Inputs!F10+Inputs!F11+Inputs!F12+(D5*12*(1-D6))*Inputs!F13+(D5*12*(1-D6))*Inputs!F14 -> 106185.6 | E15: =Inputs!F10+Inputs!F11+Inputs!F12+(E5*12*(1-E6))*Inputs!F13+(E5*12*(1-E6))*Inputs!F14 -> 115420.8
B16: NOI (₹) | C16: =((C5*12*(1-C6))-Inputs!F10-Inputs!F11-Inputs!F12-(C5*12*(1-C6))*Inputs!F13-(C5*12*(1-C6))*Inputs!F14) -> 111480 | D16: =((D5*12*(1-D6))-Inputs!F10-Inputs!F11-Inputs!F12-(D5*12*(1-D6))*Inputs!F13-(D5*12*(1-D6))*Inputs!F14) -> 202934.4 | E16: =((E5*12*(1-E6))-Inputs!F10-Inputs!F11-Inputs!F12-(E5*12*(1-E6))*Inputs!F13-(E5*12*(1-E6))*Inputs!F14) -> 264739.2
B17: Annual EMI (₹) | C17: =(IFERROR((Inputs!C13*(1-Inputs!C19))*C9/12*(1+C9/12)^(C11*12)/((1+C9/12)^(C11*12)-1),0))*12 -> 1106202.7 | D17: =(IFERROR((Inputs!C13*(1-Inputs!C19))*D9/12*(1+D9/12)^(D11*12)/((1+D9/12)^(D11*12)-1),0))*12 -> 1082823.1 | E17: =(IFERROR((Inputs!C13*(1-Inputs!C19))*E9/12*(1+E9/12)^(E11*12)/((1+E9/12)^(E11*12)-1),0))*12 -> 1071236.4
B18: Net Cash Flow (₹) | C18: =(((C5*12*(1-C6))-Inputs!F10-Inputs!F11-Inputs!F12-(C5*12*(1-C6))*Inputs!F13-(C5*12*(1-C6))*Inputs!F14)-(IFERROR((Inputs!C13*(1-Inputs!C19))*C9/12*(1+C9/12)^(C11*12)/((1+C9/12)^(C11*12)-1),0))*12) -> -994722.72 | D18: =(((D5*12*(1-D6))-Inputs!F10-Inputs!F11-Inputs!F12-(D5*12*(1-D6))*Inputs!F13-(D5*12*(1-D6))*Inputs!F14)-(IFERROR((Inputs!C13*(1-Inputs!C19))*D9/12*(1+D9/12)^(D11*12)/((1+D9/12)^(D11*12)-1),0))*12) -> -879888.72 | E18: =(((E5*12*(1-E6))-Inputs!F10-Inputs!F11-Inputs!F12-(E5*12*(1-E6))*Inputs!F13-(E5*12*(1-E6))*Inputs!F14)-(IFERROR((Inputs!C13*(1-Inputs!C19))*E9/12*(1+E9/12)^(E11*12)/((1+E9/12)^(E11*12)-1),0))*12) -> -806497.15
B20: Gross yield (%) | C20: =C5*12/Inputs!C13 -> 0.026666667 | D20: =D5*12/Inputs!C13 -> 0.037333333 | E20: =E5*12/Inputs!C13 -> 0.044
B21: Cap rate (%) | C21: =((C5*12*(1-C6))-Inputs!F10-Inputs!F11-Inputs!F12-(C5*12*(1-C6))*Inputs!F13-(C5*12*(1-C6))*Inputs!F14)/Inputs!C13 -> 0.012386667 | D21: =((D5*12*(1-D6))-Inputs!F10-Inputs!F11-Inputs!F12-(D5*12*(1-D6))*Inputs!F13-(D5*12*(1-D6))*Inputs!F14)/Inputs!C13 -> 0.022548267 | E21: =((E5*12*(1-E6))-Inputs!F10-Inputs!F11-Inputs!F12-(E5*12*(1-E6))*Inputs!F13-(E5*12*(1-E6))*Inputs!F14)/Inputs!C13 -> 0.029415467
B22: Cash-on-cash (%) | C22: =IF((Inputs!C13*Inputs!C19+Inputs!C13*Inputs!C14+Inputs!C15+Inputs!C23)>0,(((C5*12*(1-C6))-Inputs!F10-Inputs!F11-Inputs!F12-(C5*12*(1-C6))*Inputs!F13-(C5*12*(1-C6))*Inputs!F14)-(IFERROR((Inputs!C13*(1-Inputs!C19))*C9/12*(1+C9/12)^(C11*12)/((1+C9/12)^(C11*12)-1),0))*12)/(Inputs!C13*Inputs!C19+Inputs!C13*Inputs!C14+Inputs!C15+Inputs!C23),0) -> -0.38406283 | D22: =IF((Inputs!C13*Inputs!C19+Inputs!C13*Inputs!C14+Inputs!C15+Inputs!C23)>0,(((D5*12*(1-D6))-Inputs!F10-Inputs!F11-Inputs!F12-(D5*12*(1-D6))*Inputs!F13-(D5*12*(1-D6))*Inputs!F14)-(IFERROR((Inputs!C13*(1-Inputs!C19))*D9/12*(1+D9/12)^(D11*12)/((1+D9/12)^(D11*12)-1),0))*12)/(Inputs!C13*Inputs!C19+Inputs!C13*Inputs!C14+Inputs!C15+Inputs!C23),0) -> -0.33972538 | E22: =IF((Inputs!C13*Inputs!C19+Inputs!C13*Inputs!C14+Inputs!C15+Inputs!C23)>0,(((E5*12*(1-E6))-Inputs!F10-Inputs!F11-Inputs!F12-(E5*12*(1-E6))*Inputs!F13-(E5*12*(1-E6))*Inputs!F14)-(IFERROR((Inputs!C13*(1-Inputs!C19))*E9/12*(1+E9/12)^(E11*12)/((1+E9/12)^(E11*12)-1),0))*12)/(Inputs!C13*Inputs!C19+Inputs!C13*Inputs!C14+Inputs!C15+Inputs!C23),0) -> -0.31138886
B24: Projected sale price (₹) | C24: =(Inputs!C13*(1+C8)^C11) -> 13322199 | D24: =(Inputs!C13*(1+D8)^D11) -> 17704362 | E24: =(Inputs!C13*(1+E8)^E11) -> 23343682
B25: Net sale proceeds (₹) | C25: =((Inputs!C13*(1+C8)^C11)*(1-C10)-((Inputs!C13*(1+C8)^C11)-Inputs!C13)*Inputs!F32) -> 12058093 | D25: =((Inputs!C13*(1+D8)^D11)*(1-D10)-((Inputs!C13*(1+D8)^D11)-Inputs!C13)*Inputs!F32) -> 15609403 | E25: =((Inputs!C13*(1+E8)^E11)*(1-E10)-((Inputs!C13*(1+E8)^E11)-Inputs!C13)*Inputs!F32) -> 20124790

Sheet Comparison
B1: PROPERTY COMPARISON TOOL — Up to 3 Properties
B2: Enter details for up to 3 properties. Blue = inputs. Outputs calculated automatically.
B4: Input / Metric | C4: Property A | D4: Property B | E4: Property C
B5: Property name | C5: Property A | D5: Property B | E5: Property C
B6: Purchase price (₹) | C6: 9000000 | D6: 12000000 | E6: 6500000
B7: Built-up area (sq ft) | C7: 1200 | D7: 1600 | E7: 900
B8: Monthly rent (₹) | C8: 28000 | D8: 38000 | E8: 21000
B9: Annual appreciation (%) | C9: 0.07 | D9: 0.065 | E9: 0.08
B10: Down payment (%) | C10: 0.2 | D10: 0.2 | E10: 0.2
B11: Loan rate (% p.a.) | C11: 0.0875 | D11: 0.0875 | E11: 0.0875
B12: Hold period (years) | C12: 10 | D12: 10 | E12: 10
B13: Vacancy rate (%) | C13: 0.08 | D13: 0.08 | E13: 0.08
B14: Annual expenses (₹) | C14: 72000 | D14: 95000 | E14: 55000
B16: CALCULATED METRICS
B17: Effective income (₹) | C17: =(C8*12*(1-C13)) -> 309120 | D17: =(D8*12*(1-D13)) -> 419520 | E17: =(E8*12*(1-E13)) -> 231840
B18: Total expenses (₹) | C18: =C14 -> 72000 | D18: =D14 -> 95000 | E18: =E14 -> 55000
B19: NOI (₹) | C19: =((C8*12*(1-C13))-C14) -> 237120 | D19: =((D8*12*(1-D13))-D14) -> 324520 | E19: =((E8*12*(1-E13))-E14) -> 176840
B20: Annual EMI (₹) | C20: =IFERROR((C6*(1-C10))*C11/12*(1+C11/12)^(C12*12)/((1+C11/12)^(C12*12)-1)*12,0) -> 1082823.1 | D20: =IFERROR((D6*(1-D10))*D11/12*(1+D11/12)^(D12*12)/((1+D11/12)^(D12*12)-1)*12,0) -> 1443764.2 | E20: =IFERROR((E6*(1-E10))*E11/12*(1+E11/12)^(E12*12)/((1+E11/12)^(E12*12)-1)*12,0) -> 782038.92
B21: Net cash flow (₹) | C21: =(((C8*12*(1-C13))-C14)-IFERROR((C6*(1-C10))*C11/12*(1+C11/12)^(C12*12)/((1+C11/12)^(C12*12)-1)*12,0)) -> -845703.12 | D21: =(((D8*12*(1-D13))-D14)-IFERROR((D6*(1-D10))*D11/12*(1+D11/12)^(D12*12)/((1+D11/12)^(D12*12)-1)*12,0)) -> -1119244.2 | E21: =(((E8*12*(1-E13))-E14)-IFERROR((E6*(1-E10))*E11/12*(1+E11/12)^(E12*12)/((1+E11/12)^(E12*12)-1)*12,0)) -> -605198.92
B23: Gross yield (%) | C23: =C8*12/C6 -> 0.037333333 | D23: =D8*12/D6 -> 0.038 | E23: =E8*12/E6 -> 0.038769231
B24: Cap rate (%) | C24: =((C8*12*(1-C13))-C14)/C6 -> 0.026346667 | D24: =((D8*12*(1-D13))-D14)/D6 -> 0.027043333 | E24: =((E8*12*(1-E13))-E14)/E6 -> 0.027206154
B25: CoC return (%) | C25: =IF((C6*C10)>0,(((C8*12*(1-C13))-C14)-IFERROR((C6*(1-C10))*C11/12*(1+C11/12)^(C12*12)/((1+C11/12)^(C12*12)-1)*12,0))/(C6*C10),0) -> -0.46983507 | D25: =IF((D6*D10)>0,(((D8*12*(1-D13))-D14)-IFERROR((D6*(1-D10))*D11/12*(1+D11/12)^(D12*12)/((1+D11/12)^(D12*12)-1)*12,0))/(D6*D10),0) -> -0.46635174 | E25: =IF((E6*E10)>0,(((E8*12*(1-E13))-E14)-IFERROR((E6*(1-E10))*E11/12*(1+E11/12)^(E12*12)/((1+E11/12)^(E12*12)-1)*12,0))/(E6*E10),0) -> -0.46553763
B26: Price per sq ft (₹) | C26: =IF(C7>0,C6/C7,0) -> 7500 | D26: =IF(D7>0,D6/D7,0) -> 7500 | E26: =IF(E7>0,E6/E7,0) -> 7222.2222
B28: Projected sale price (₹) | C28: =(C6*(1+C9)^C12) -> 17704362 | D28: =(D6*(1+D9)^D12) -> 22525650 | E28: =(E6*(1+E9)^E12) -> 14033012
B29: Net sale proceeds (₹) | C29: =(C6*(1+C9)^C12)*0.98-((C6*(1+C9)^C12)-C6)*0.2 -> 15609403 | D29: =(D6*(1+D9)^D12)*0.98-((D6*(1+D9)^D12)-D6)*0.2 -> 19970007 | E29: =(E6*(1+E9)^E12)*0.98-((E6*(1+E9)^E12)-E6)*0.2 -> 12245750
